adsputils/__init__.py
adsputils/exceptions.py
adsputils/serializer.py
adsputils/tests/__init__.py
adsputils/tests/config_sample.py
adsputils/tests/test_app.py
adsputils/tests/test_init.py
adsputils/tests/test_serializer.py
adsputils/tests/test_utils.py
adsputils-1.5.15.dist-info/LICENSE
adsputils-1.5.15.dist-info/METADATA
adsputils-1.5.15.dist-info/WHEEL
adsputils-1.5.15.dist-info/top_level.txt
adsputils-1.5.15.dist-info/RECORD
