Metadata-Version: 2.1
Name: adsputils
Version: 1.5.15
Summary: ADS Pipeline Utils
Home-page: https://github.com/adsabs/ADSPipelineUtils
Author: NASA/SAO ADS
License: MIT
Platform: any
Classifier: Programming Language :: Python :: 2.7
Classifier: Programming Language :: Python :: 3
Classifier: Programming Language :: Python :: 3.7
Classifier: License :: OSI Approved :: MIT License
License-File: LICENSE
Requires-Dist: adsmsg==1.3.18
Requires-Dist: concurrent-log-handler==0.9.20
Requires-Dist: python-dateutil==2.9.0.post0
Requires-Dist: DateTime==4.1.1
Requires-Dist: celery==4.4.2
Requires-Dist: SQLAlchemy==1.4.50
Requires-Dist: python-json-logger==0.1.8
Requires-Dist: setuptools<45
Requires-Dist: unidecode==1.2.0
Requires-Dist: requests==2.27.1
Requires-Dist: future==0.18.2
